{
  "project_info": {
    "project_number": "446181163107",
    "project_id": "recyclerview-3960b",
    "storage_bucket": "recyclerview-3960b.appspot.com"
  },
  "client": [
    {
      "client_info": {
        "mobilesdk_app_id": "1:446181163107:android:3f7a943a759c9c48e6b856",
        "android_client_info": {
          "package_name": "com.fery.recyclerview"
        }
      },
      "oauth_client": [],
      "api_key": [
        {
          "current_key": "AIzaSyCQH-zi5HQHuEgHkGWB0lIoF_S7QiH78KA"
        }
      ],
      "services": {
        "appinvite_service": {
          "other_platform_oauth_client": []
        }
      }
    }
  ],
  "configuration_version": "1"
}